ppillar.py
setup.cfg
setup.py
ppillar.egg-info/PKG-INFO
ppillar.egg-info/SOURCES.txt
ppillar.egg-info/dependency_links.txt
ppillar.egg-info/entry_points.txt
ppillar.egg-info/requires.txt
ppillar.egg-info/top_level.txt