Metadata-Version: 1.1
Name: ppillar
Version: 0.1.2
Summary: A PKI encrypted datastructure to keep secrets in the public
Home-page: https://github.com/thusoy/public-pillar
Author: Tarjei Husøy
Author-email: tarjei@roms.no
License: UNKNOWN
Platform: UNKNOWN
Classifier: Development Status :: 3 - Alpha
Classifier: Environment :: Web Environment
Classifier: Intended Audience :: Developers
Classifier: Intended Audience :: Information Technology
Classifier: Intended Audience :: System Administrators
Classifier: License :: OSI Approved :: MIT License
Classifier: Programming Language :: Python :: 2.7
Classifier: Topic :: Security
